pyromname/__init__.py
pyromname/cli.py
pyromname/crc.py
pyromname/file.py
pyromname/io.py
pyromname/renascene.py
pyromname/rom_database.py
pyromname/rom_database_3dsdb.py
pyromname/rom_database_dat.py
pyromname/seven_zip.py
pyromname/ui.py
pyromname/zip.py
pyromname-1.0.0.dist-info/METADATA
pyromname-1.0.0.dist-info/WHEEL
pyromname-1.0.0.dist-info/entry_points.txt
pyromname-1.0.0.dist-info/RECORD
