Metadata-Version: 2.1
Name: pyromname
Version: 1.0.0
Summary: pyromname is a command line tool to manage roms.
Author: Mathieu
Author-email: git@bigbisous.org
Requires-Python: >=3.9,<4.0
Classifier: Programming Language :: Python :: 3
Classifier: Programming Language :: Python :: 3.9
Classifier: Programming Language :: Python :: 3.10
Classifier: Programming Language :: Python :: 3.11
Requires-Dist: colorama (>=0.4.6,<0.5.0)
Requires-Dist: defusedxml (>=0.7.1,<0.8.0)
